{"skeleton":{"hash":"FvQssUbnhVdjWPMzIsnxdUE1C3g","spine":"2.1.27","width":167.02,"height":172.08,"images":"./images/"},"bones":[{"name":"root","scaleX":0.2,"scaleY":0.2},{"name":"bone","parent":"root","x":-1033.51,"y":1959.77,"rotation":-4.38},{"name":"bone2","parent":"root","x":-627.46,"y":1947.23},{"name":"bone3","parent":"root","x":-1128.98,"y":1433.25}],"slots":[{"name":"1012se01","bone":"bone","attachment":"1012se01"},{"name":"1012se02","bone":"bone3","attachment":"1012se02"},{"name":"1012se030001","bone":"bone2","attachment":"1012se030001"}],"skins":{"default":{"1012se01":{"1012se01":{"x":-14.56,"y":16.26,"scaleX":-5,"scaleY":5,"width":83,"height":78}},"1012se02":{"1012se02":{"x":14.33,"y":3.22,"scaleX":-5,"scaleY":5,"width":89,"height":34}},"1012se030001":{"1012se030001":{"x":-7.06,"y":104.66,"scaleX":-5,"scaleY":5,"width":53,"height":64},"1012se030002":{"x":-7.06,"y":104.66,"scaleX":-5,"scaleY":5,"width":62,"height":136},"1012se030003":{"x":-7.06,"y":104.66,"scaleX":-5,"scaleY":5,"width":76,"height":156},"1012se030004":{"x":-7.06,"y":104.66,"scaleX":-5,"scaleY":5,"width":86,"height":142},"1012se030005":{"x":-7.06,"y":104.66,"scaleX":-5,"scaleY":5,"width":86,"height":142},"1012se030006":{"x":-7.06,"y":104.66,"scaleX":-5,"scaleY":5,"width":83,"height":136}}}},"animations":{"play01":{"slots":{"1012se02":{"color":[{"time":0,"color":"ffffff00"}]},"1012se030001":{"color":[{"time":0,"color":"ffffff00"}]}},"bones":{"root":{"rotate":[{"time":0,"angle":0}],"translate":[{"time":0,"x":0,"y":0}],"scale":[{"time":0,"x":1,"y":1}]},"bone":{"rotate":[{"time":0,"angle":0},{"time":0.1333,"angle":-137.39},{"time":0.2666,"angle":112.73},{"time":0.4,"angle":0}],"translate":[{"time":0,"x":1033.51,"y":-1959.77,"curve":"stepped"},{"time":0.4,"x":1033.51,"y":-1959.77}],"scale":[{"time":0,"x":1,"y":1,"curve":"stepped"},{"time":0.4,"x":1,"y":1}]}}},"play02":{"slots":{"1012se01":{"attachment":[{"time":0,"name":"1012se01"}],"color":[{"time":0,"color":"ffffffff"},{"time":0.0666,"color":"ffffff00"}]},"1012se02":{"color":[{"time":0,"color":"ffffffff","curve":"stepped"},{"time":0.1,"color":"ffffffff"},{"time":0.2333,"color":"ffffff00"}]},"1012se030001":{"attachment":[{"time":0,"name":"1012se030001"},{"time":0.0333,"name":"1012se030002"},{"time":0.0666,"name":"1012se030003"},{"time":0.1,"name":"1012se030004"},{"time":0.1333,"name":"1012se030005"},{"time":0.1666,"name":"1012se030006"}],"color":[{"time":0.2333,"color":"ffffffff"},{"time":0.3666,"color":"ffffff00"}]}},"bones":{"root":{"rotate":[{"time":0,"angle":0}],"translate":[{"time":0,"x":0,"y":0}],"scale":[{"time":0,"x":1,"y":1}]},"bone":{"rotate":[{"time":0,"angle":0}],"translate":[{"time":0,"x":1033.51,"y":-1913.17}],"scale":[{"time":0,"x":1,"y":1}]},"bone3":{"rotate":[{"time":0,"angle":0}],"translate":[{"time":0,"x":1133.23,"y":-1408.87}],"scale":[{"time":0,"x":1.865,"y":1.865},{"time":0.1,"x":3.164,"y":3.164},{"time":0.2333,"x":3.392,"y":3.392}]},"bone2":{"rotate":[{"time":0,"angle":0,"curve":"stepped"},{"time":0.2333,"angle":0}],"translate":[{"time":0,"x":625.72,"y":-1937.17},{"time":0.0333,"x":625.72,"y":-1646.25},{"time":0.0666,"x":625.72,"y":-1510.19},{"time":0.1,"x":625.72,"y":-1426.85},{"time":0.2333,"x":625.72,"y":-1311.62},{"time":0.3666,"x":625.72,"y":-1330.56}],"scale":[{"time":0,"x":1.608,"y":1.608,"curve":"stepped"},{"time":0.2333,"x":1.608,"y":1.608},{"time":0.3666,"x":1.797,"y":1.864}]}}}}}